SlackLogger/__init__.py
SlackLogger/version.py
logging_slackhandler-2.5.0.dist-info/DESCRIPTION.rst
logging_slackhandler-2.5.0.dist-info/METADATA
logging_slackhandler-2.5.0.dist-info/RECORD
logging_slackhandler-2.5.0.dist-info/WHEEL
logging_slackhandler-2.5.0.dist-info/metadata.json
logging_slackhandler-2.5.0.dist-info/top_level.txt
