Metadata-Version: 2.0
Name: logging-slackhandler
Version: 2.5.0
Summary: A logging handler for Slack
Home-page: https://github.com/Greums/logging-slackhandler
Author: Damien Le Bourdonnec
Author-email: greumsworkshop@gmail.com
License: MIT
Download-URL: https://github.com/Greums/logging-slackhandler/tarball/2.5.0
Keywords: logging slack
Platform: any
Classifier: Development Status :: 5 - Production/Stable
Classifier: Intended Audience :: Developers
Classifier: Topic :: Software Development :: Libraries :: Python Modules
Classifier: Topic :: Communications :: Chat
Classifier: Topic :: System :: Logging
Classifier: License :: OSI Approved :: MIT License
Classifier: Programming Language :: Python :: 2
Classifier: Programming Language :: Python :: 2.7
Classifier: Programming Language :: Python :: 3
Classifier: Programming Language :: Python :: 3.3
Classifier: Programming Language :: Python :: 3.4
Classifier: Programming Language :: Python :: 3.5
Classifier: Programming Language :: Python :: 3.6
